qtcompat/__init__.py
qtcompat/__version__.py
qtcompat-0.0.1a0.dist-info/METADATA
qtcompat-0.0.1a0.dist-info/WHEEL
qtcompat-0.0.1a0.dist-info/top_level.txt
qtcompat-0.0.1a0.dist-info/RECORD
