Metadata-Version: 2.1
Name: qtcompat
Version: 0.0.1a0
Summary: qtcompat
Home-page: https://bitbucket.org/bvidmar/qtcompat
Author: Roberto Vidmar
Author-email: rvidmar@inogs.it, ncreati@inogs.it
License: MIT
Download-URL: https://bitbucket.org/bvidmar/qtcompat/
Keywords: qtcompat,PySide2,PyQt5,PySide6
Platform: POSIX
Classifier: Development Status :: 3 - Alpha
Classifier: Intended Audience :: Developers
Classifier: Intended Audience :: Science/Research
Classifier: License :: OSI Approved :: MIT License
Classifier: Operating System :: POSIX
Classifier: Programming Language :: Python
Classifier: Topic :: Scientific/Engineering
Classifier: Topic :: Software Development :: Libraries
Requires-Dist: pip (>=20.0.2)
Requires-Dist: setuptools (>=45.2.0)
